{
	"site": "KFL",
	"name": "Kids Foot Locker",
	"brand": {
		"primary": "$science_blue",
		"secondary": "$mineshaft",
		"highlight": "$science_blue",
		"black": "$mineshaft",
		"grey": "$emperor"
	},
	"font": {
		"family": {
			"base": "Roboto",
			"heading": "Poppins",
			"mono": "RobotoMono"
		}
	},
	"theme": {
		"light": {
			"css": {
				"color": "$black",
				"background-color": "$white"
			},
			"button": {
				"primary": {
					"color": "$black",
					"border-color": "$white",
					"background-color": "$white"
				},
				"secondary": {
					"color": "$white",
					"border-color": "$white",
					"background-color": "$black"
				}
			}
		},
		"dark": {
			"color": "$white",
			"background-color": "$mineshaft"
		},
		"accent": {
			"color": "$white",
			"background-color": "$brand_primary"
		}
	}
}
